num_tool/__init__.py
num_tool/num_tool.py
num_tool-0.0.20.dist-info/METADATA
num_tool-0.0.20.dist-info/WHEEL
num_tool-0.0.20.dist-info/top_level.txt
num_tool-0.0.20.dist-info/RECORD
