Metadata-Version: 2.1
Name: num-tool
Version: 0.0.20
Summary: A basic number tools package
Home-page: UNKNOWN
Author: totensee (Ruben Pérez Krüger)
Author-email: <churrerico@web.de>
License: MIT
Keywords: python,random,number,tools
Platform: UNKNOWN
Classifier: Development Status :: 1 - Planning
Classifier: Intended Audience :: Developers
Classifier: Programming Language :: Python :: 3
Classifier: Operating System :: Unix
Classifier: Operating System :: MacOS :: MacOS X
Classifier: Operating System :: Microsoft :: Windows
